__init__.py
flim_labs_api.py
flim_labs_api-1.0.0.dist-info/LICENSE
flim_labs_api-1.0.0.dist-info/METADATA
flim_labs_api-1.0.0.dist-info/WHEEL
flim_labs_api-1.0.0.dist-info/top_level.txt
flim_labs_api-1.0.0.dist-info/RECORD
