Metadata-Version: 2.1
Name: flim-labs-api
Version: 1.0.0
Summary: Python API developed for controlling, acquiring and displaying time tagged fluorescence photons' data streamed from a data acquisition card based on FPGA technology in order to perform real time Fluorescence Lifetime Imaging (FLIM) and Spectroscopy applications.
Author-email: Stefano Tucci <tux@living-on.dev>
License: GNU AFFERO GENERAL PUBLIC LICENSE
Project-URL: Homepage, https://github.com/FLIMLABS
Keywords: flim
Classifier: License :: OSI Approved :: GNU Affero General Public License v3
Classifier: Programming Language :: Python
Classifier: Programming Language :: Python :: 3
Requires-Python: >=3.10
License-File: LICENSE
Requires-Dist: contourpy (==1.0.7)
Requires-Dist: cycler (==0.11.0)
Requires-Dist: fonttools (==4.38.0)
Requires-Dist: kiwisolver (==1.4.4)
Requires-Dist: matplotlib (==3.6.3)
Requires-Dist: numpy (==1.24.1)
Requires-Dist: packaging (==23.0)
Requires-Dist: Pillow (==9.4.0)
Requires-Dist: psutil (==5.9.4)
Requires-Dist: pyparsing (==3.0.9)
Requires-Dist: PyQt5 (==5.15.7)
Requires-Dist: PyQt5-Qt5 (==5.15.2)
Requires-Dist: PyQt5-sip (==12.11.0)
Requires-Dist: python-dateutil (==2.8.2)
Requires-Dist: pyzmq (==25.0.0)
Requires-Dist: six (==1.16.0)
